{"request":{"event":"ONAPPINSTALL","event_handler_id":"5","data":{"VERSION":"1","ACTIVE":"Y","INSTALLED":"Y","LANGUAGE_ID":"ru"},"ts":"1745652409","auth":{"access_token":"c9980c68007819a800761d62000000010000073fca381282f3391af620d142e15f7b81","expires":"1745656009","expires_in":"3600","scope":"crm,placement,im","domain":"cg96022.tw1.ru","server_endpoint":"https:\/\/oauth.bitrix.info\/rest\/","status":"L","client_endpoint":"https:\/\/cg96022.tw1.ru\/rest\/","member_id":"e73db48ec79ed272edfb894d8d6d88e0","user_id":"1","refresh_token":"b9173468007819a800761d62000000010000071bd57055d0d8039ce98cd9142bbad60a","application_token":"1a07baef456c3c7018a5b0a6118e0d97"}},"result":{"rest_only":true,"install":true}}